simplay_jupyter/__init__.py
simplay_jupyter/_version.py
simplay_jupyter-1.0.1.data/data/share/jupyter/labextensions/simplay_jupyter/package.json
simplay_jupyter-1.0.1.data/data/share/jupyter/labextensions/simplay_jupyter/static/376.4d1704cf97efd1bae864.js
simplay_jupyter-1.0.1.data/data/share/jupyter/labextensions/simplay_jupyter/static/376.4d1704cf97efd1bae864.js.LICENSE.txt
simplay_jupyter-1.0.1.data/data/share/jupyter/labextensions/simplay_jupyter/static/476.693723deec8690778432.js
simplay_jupyter-1.0.1.data/data/share/jupyter/labextensions/simplay_jupyter/static/479.0466e86e6949ae1c1d8a.js
simplay_jupyter-1.0.1.data/data/share/jupyter/labextensions/simplay_jupyter/static/747.8fa7a6ed4dff7ec9e662.js
simplay_jupyter-1.0.1.data/data/share/jupyter/labextensions/simplay_jupyter/static/remoteEntry.5f1c737c7537e6e75cf6.js
simplay_jupyter-1.0.1.data/data/share/jupyter/labextensions/simplay_jupyter/static/style.js
simplay_jupyter-1.0.1.data/data/share/jupyter/labextensions/simplay_jupyter/static/third-party-licenses.json
simplay_jupyter-1.0.1.data/data/share/jupyter/labextensions/simplay_jupyter/install.json
simplay_jupyter-1.0.1.dist-info/METADATA
simplay_jupyter-1.0.1.dist-info/WHEEL
simplay_jupyter-1.0.1.dist-info/licenses/LICENSE
simplay_jupyter-1.0.1.dist-info/RECORD
